pyisocode/__init__.py
pyisocode-0.0.1.dist-info/LICENCE.txt
pyisocode-0.0.1.dist-info/METADATA
pyisocode-0.0.1.dist-info/WHEEL
pyisocode-0.0.1.dist-info/top_level.txt
pyisocode-0.0.1.dist-info/RECORD
